postal_code/__init__.py
postal_code/choices.py
postal_code/utils.py
django_postalcode-1.3.dist-info/LICENSE
django_postalcode-1.3.dist-info/METADATA
django_postalcode-1.3.dist-info/WHEEL
django_postalcode-1.3.dist-info/top_level.txt
django_postalcode-1.3.dist-info/RECORD
