Metadata-Version: 2.1
Name: django-postalcode
Version: 1.3
Summary: django-postalcode
Home-page: https://github.com/InnonationTeam/django-postalcode
Author: Jessica Chiara Catania, Rosario Amantia, Gianluca Di Franco
License: BSD
Platform: UNKNOWN
Requires-Python: >=3.6
License-File: LICENSE
Requires-Dist: Django (>=2.2.0)
